whosspr/__init__.py
whosspr/cli.py
whosspr/config.py
whosspr/controller.py
whosspr/enhancer.py
whosspr/inserter.py
whosspr/keyboard.py
whosspr/permissions.py
whosspr/recorder.py
whosspr/transcriber.py
whosspr-0.1.0.dist-info/METADATA
whosspr-0.1.0.dist-info/WHEEL
whosspr-0.1.0.dist-info/entry_points.txt
whosspr-0.1.0.dist-info/licenses/LICENSE
whosspr-0.1.0.dist-info/RECORD
