Metadata-Version: 2.4
Name: whosspr
Version: 0.1.0
Summary: WhOSSpr Flow - Open Source Speech-to-Text for macOS
License-Expression: Apache-2.0
License-File: LICENSE
Requires-Python: >=3.12
Requires-Dist: numpy>=1.24.0
Requires-Dist: openai-whisper>=20240930
Requires-Dist: openai>=1.0.0
Requires-Dist: pydantic>=2.0.0
Requires-Dist: pynput>=1.7.6
Requires-Dist: pyperclip>=1.8.0
Requires-Dist: rich>=13.0.0
Requires-Dist: sounddevice>=0.4.6
Requires-Dist: typer>=0.9.0
Provides-Extra: dev
Requires-Dist: pytest-asyncio>=0.21.0; extra == 'dev'
Requires-Dist: pytest-cov>=4.0.0; extra == 'dev'
Requires-Dist: pytest>=7.0.0; extra == 'dev'
